{
    "gamestats": {},
    "progression": {},
    "starship": {
        "computed_stats": {},
        "hull": {
            "models": [
                "hardened_marsian_armor"
            ],
            "secondary_weapon_mount_slots": 2
        },
        "weaponry": {
            "primary": {
                "model": "basic_orbital_debris_accelerator"
            },
            "secondary": [
                {
                    "slot": 1,
                    "model": "damaged_artillery"
                },
                {
                    "slot": 2,
                    "model": "damaged_artillery"
                }
            ]
        },
        "engine": {
            "model": "spiralling_reactor"
        },
        "thrusters": {
            "model": "pre_war_era_propulsion_thrusters"
        }
    }
}